wildtime/__init__.py
wildtime/baseline_trainer.py
wildtime/config.py
wildtime/configs_builder.py
wildtime/dataloader.py
wildtime/main.py
wildtime/configs/__init__.py
wildtime/configs/eval_fix/__init__.py
wildtime/configs/eval_fix/configs_arxiv.py
wildtime/configs/eval_fix/configs_drug.py
wildtime/configs/eval_fix/configs_fmow.py
wildtime/configs/eval_fix/configs_huffpost.py
wildtime/configs/eval_fix/configs_mimic_mortality.py
wildtime/configs/eval_fix/configs_mimic_readmission.py
wildtime/configs/eval_fix/configs_yearbook.py
wildtime/configs/eval_stream/__init__.py
wildtime/configs/eval_stream/configs_arxiv.py
wildtime/configs/eval_stream/configs_drug.py
wildtime/configs/eval_stream/configs_fmow.py
wildtime/configs/eval_stream/configs_huffpost.py
wildtime/configs/eval_stream/configs_mimic_mortality.py
wildtime/configs/eval_stream/configs_mimic_readmission.py
wildtime/configs/eval_stream/configs_yearbook.py
wildtime/data/__init__.py
wildtime/data/arxiv.py
wildtime/data/drug.py
wildtime/data/fmow.py
wildtime/data/huffpost.py
wildtime/data/mimic.py
wildtime/data/utils.py
wildtime/data/yearbook.py
wildtime/methods/__init__.py
wildtime/methods/base_trainer.py
wildtime/methods/dataloaders.py
wildtime/methods/lisa.py
wildtime/methods/mixup.py
wildtime/methods/utils.py
wildtime/methods/agem/__init__.py
wildtime/methods/agem/agem.py
wildtime/methods/agem/buffer.py
wildtime/methods/coral/__init__.py
wildtime/methods/coral/coral.py
wildtime/methods/erm/__init__.py
wildtime/methods/erm/erm.py
wildtime/methods/ewc/__init__.py
wildtime/methods/ewc/ewc.py
wildtime/methods/ft/__init__.py
wildtime/methods/ft/ft.py
wildtime/methods/groupdro/__init__.py
wildtime/methods/groupdro/groupdro.py
wildtime/methods/groupdro/loss.py
wildtime/methods/irm/__init__.py
wildtime/methods/irm/irm.py
wildtime/methods/si/__init__.py
wildtime/methods/si/si.py
wildtime/methods/simclr/__init__.py
wildtime/methods/simclr/simclr.py
wildtime/methods/swa/__init__.py
wildtime/methods/swa/swa.py
wildtime-1.1.3.dist-info/LICENSE
wildtime-1.1.3.dist-info/METADATA
wildtime-1.1.3.dist-info/WHEEL
wildtime-1.1.3.dist-info/top_level.txt
wildtime-1.1.3.dist-info/RECORD
