Metadata-Version: 2.1
Name: wildtime
Version: 1.1.3
Summary: WILDS distribution shift benchmark
Home-page: https://wilds.stanford.edu
Author: wildtime team
Author-email: wilds@cs.stanford.edu
License: MIT
Classifier: Topic :: Scientific/Engineering :: Artificial Intelligence
Classifier: Intended Audience :: Science/Research
Classifier: Programming Language :: Python :: 3
Classifier: License :: OSI Approved :: MIT License
Requires-Python: >=3.8
License-File: LICENSE
Requires-Dist: gdown (==4.5.1)
Requires-Dist: ipdb (==0.13.9)
Requires-Dist: lightly (==1.2.27)
Requires-Dist: matplotlib (==3.5.0)
Requires-Dist: numpy (==1.19.5)
Requires-Dist: omegaconf (==2.0.6)
Requires-Dist: pandas (>=1.1.3)
Requires-Dist: Pillow (==9.2.0)
Requires-Dist: pytorch-lightning (==1.3.6)
Requires-Dist: scikit-learn (==1.1.2)
Requires-Dist: PyTDC (==0.3.7)
Requires-Dist: pytorch-tabular (==0.7.0)
Requires-Dist: torchcontrib (==0.0.2)
Requires-Dist: torchvision (>=0.8.1)
Requires-Dist: torchmetrics (==0.6.0)
Requires-Dist: transformers (==4.21.1)
Requires-Dist: wilds (==2.0.0)
